ebtorch/__init__.py
ebtorch/data/__init__.py
ebtorch/data/cutmixup.py
ebtorch/data/datasets.py
ebtorch/data/prep.py
ebtorch/data/tinyimagenet.py
ebtorch/distributed/__init__.py
ebtorch/distributed/qol.py
ebtorch/distributed/slurm.py
ebtorch/logging/__init__.py
ebtorch/logging/avgmeter.py
ebtorch/logging/logcsv.py
ebtorch/logging/yamldump.py
ebtorch/nn/__init__.py
ebtorch/nn/architectures.py
ebtorch/nn/architectures_resnets_dm.py
ebtorch/nn/convolutional_flatten.py
ebtorch/nn/convstems.py
ebtorch/nn/coordconv.py
ebtorch/nn/debuglayers.py
ebtorch/nn/fieldtransform.py
ebtorch/nn/kwta.py
ebtorch/nn/laplacenet.py
ebtorch/nn/mish.py
ebtorch/nn/nnsemble.py
ebtorch/nn/penalties.py
ebtorch/nn/reshapelayers.py
ebtorch/nn/serf.py
ebtorch/nn/serlu.py
ebtorch/nn/sinlu.py
ebtorch/nn/smelu.py
ebtorch/nn/telu.py
ebtorch/nn/functional/__init__.py
ebtorch/nn/functional/inner_functional.py
ebtorch/nn/utils/__init__.py
ebtorch/nn/utils/actab.py
ebtorch/nn/utils/adverutils.py
ebtorch/nn/utils/attrsutils.py
ebtorch/nn/utils/autoclip.py
ebtorch/nn/utils/cacher.py
ebtorch/nn/utils/evalutils.py
ebtorch/nn/utils/filtermanip.py
ebtorch/nn/utils/lrfinder.py
ebtorch/nn/utils/mapply.py
ebtorch/nn/utils/numtricks.py
ebtorch/nn/utils/onlyutils.py
ebtorch/nn/utils/palettes.py
ebtorch/nn/utils/patches.py
ebtorch/nn/utils/plotting.py
ebtorch/nn/utils/reprutils.py
ebtorch/nn/utils/seeder.py
ebtorch/nn/utils/zzag.py
ebtorch/optim/__init__.py
ebtorch/optim/adabound.py
ebtorch/optim/adan.py
ebtorch/optim/adopt.py
ebtorch/optim/custom.py
ebtorch/optim/lamb.py
ebtorch/optim/lion.py
ebtorch/optim/lookahead.py
ebtorch/optim/lookaround.py
ebtorch/optim/multiphase.py
ebtorch/optim/poptims.py
ebtorch/optim/radam.py
ebtorch/optim/sam.py
ebtorch/optim/schedcos.py
ebtorch/typing/__init__.py
ebtorch/typing/customtypes.py
ebtorch-0.35.1.dist-info/licenses/LICENSE
ebtorch-0.35.1.dist-info/METADATA
ebtorch-0.35.1.dist-info/WHEEL
ebtorch-0.35.1.dist-info/top_level.txt
ebtorch-0.35.1.dist-info/RECORD
