Metadata-Version: 2.4
Name: ebtorch
Version: 0.35.1
Summary: Collection of PyTorch additions, extensions, utilities, uses and abuses
Author-email: Emanuele Ballarin <emanuele@ballarin.cc>
License: Apache-2.0
Project-URL: Homepage, https://github.com/emaballarin/ebtorch
Project-URL: Repository, https://github.com/emaballarin/ebtorch
Keywords: Deep Learning,Machine Learning
Classifier: Development Status :: 4 - Beta
Classifier: Environment :: Console
Classifier: License :: OSI Approved :: Apache Software License
Classifier: Programming Language :: Python :: 3
Classifier: Topic :: Scientific/Engineering :: Artificial Intelligence
Requires-Python: >=3.11
License-File: LICENSE
Requires-Dist: PyYAML>=6.0.3
Requires-Dist: advertorch>=0.2.3
Requires-Dist: distributed>=2025.9.1
Requires-Dist: httpx>=0.28.1
Requires-Dist: idna>=3.10
Requires-Dist: matplotlib>=3.10.6
Requires-Dist: medmnist>=3.0.2
Requires-Dist: numpy>=2.3.3
Requires-Dist: pillow>=11.3
Requires-Dist: requests>=2.32.5
Requires-Dist: safe_assert>=0.5
Requires-Dist: safetensors>=0.6.2
Requires-Dist: setuptools>=80.9
Requires-Dist: thrmt>=0.0.15
Requires-Dist: torch-lr-finder>=0.2.2
Requires-Dist: torch>=2.8
Requires-Dist: torchattacks>=3.5.1
Requires-Dist: torchvision>=0.23
Requires-Dist: tqdm>=4.67.1
Requires-Dist: urllib3>=2.5
Dynamic: license-file
